kstack/__init__.py
kstack/actions.py
kstack/console.py
kstack/deployments.py
kstack/kstack.schema.json
kstack/transformers.py
kstack/utils.py
kstack-0.1.1.dist-info/LICENSE
kstack-0.1.1.dist-info/METADATA
kstack-0.1.1.dist-info/WHEEL
kstack-0.1.1.dist-info/entry_points.txt
kstack-0.1.1.dist-info/RECORD
