Metadata-Version: 2.3
Name: kstack
Version: 0.1.1
Summary: Deploy Kubernetes clusters from simplified YAML
License: GPL-3.0-or-later
Keywords: k8s,kubernetes,cluster,deployment,devops
Author: Bruno Bernard
Author-email: brunobernard@duck.com
Requires-Python: >=3.11,<4.0
Classifier: Development Status :: 4 - Beta
Classifier: Environment :: Console
Classifier: Intended Audience :: Developers
Classifier: Intended Audience :: System Administrators
Classifier: License :: OSI Approved :: GNU General Public License v3 or later (GPLv3+)
Classifier: Programming Language :: Python :: 3
Classifier: Programming Language :: Python :: 3.11
Classifier: Programming Language :: Python :: 3.12
Classifier: Programming Language :: Python :: 3.13
Classifier: Topic :: Software Development :: Build Tools
Classifier: Topic :: System :: Systems Administration
Requires-Dist: click (>=8.1.8,<9.0.0)
Requires-Dist: halo (>=0.0.31,<0.0.32)
Requires-Dist: jsonschema (>=4.23.0,<5.0.0)
Requires-Dist: kubernetes (>=32.0.1,<33.0.0)
Requires-Dist: pyyaml (>=6.0.2,<7.0.0)
Requires-Dist: questionary (>=2.1.0,<3.0.0)
Requires-Dist: rich (>=13.9.4,<14.0.0)
Project-URL: Repository, https://github.com/eznix86/kstack
